Workbook

Sheet Assumptions
A1: Business Mentors Association — cost assumptions
A2: Blue cells are inputs. Yellow cells are the key levers. Black cells are calculated.
A4: Input | B4: Value | C4: Note
A5: Account owners with paid mailboxes | B5: 2 | C5: Ruling 18: at least two owners
A6: People in the password vault | B6: 3 | C6: Business plans require at least 3
A7: People in the request system | B7: 3 | C7: Support team size
A8: Fiscal sponsor fee | B8: 0.1 | C8: Published range 5%-15%; 3%-8% for the lighter form
A9: Contingency | B9: 0.1 | C9: Rule of thumb
A10: Anthropic nonprofit discount | B10: 0.8 | C10: Stated by Doug 09-19-26
A11: Google Workspace nonprofit price | B11: 0 | C11: Free edition once qualified (stated by Doug)
A12: Federal exemption application fee | B12: 600 | C12: $600 full form; $275 short form if receipts stay under $50,000
A13: Advanced Pack nonprofit price | B13: 295 | C13: EspoCRM nonprofit price for the Advanced Pack extension, per year (stated by Doug 09-20-26)

Sheet Recurring costs
A1: Recurring annual costs — the Association's own
A2: Column F is today's price. Column H applies the nonprofit programs once the Association qualifies. Blue = input, black = calculated.
A4: Category | B4: Item | C4: Unit price | D4: Quantity | E4: Times per year | F4: Annual — standard | G4: Nonprofit factor | H4: Annual — nonprofit | I4: Note and source
A5: Infrastructure | B5: Domain name (Cloudflare, at cost) | C5: 11 | D5: 1 | E5: 1 | F5: =C5*D5*E5 -> 11 | G5: 1 | H5: =F5*G5 -> 11 | I5: Estimate; not checked at the registrar
A6: Infrastructure | B6: Shared test system - CRM server (4 GB) | C6: 24 | D6: 1 | E6: 12 | F6: =C6*D6*E6 -> 288 | G6: 1 | H6: =F6*G6 -> 288 | I6: DigitalOcean published price
A7: Infrastructure | B7: Shared test system - server backups | C7: 4.8 | D7: 1 | E7: 12 | F7: =C7*D7*E7 -> 57.6 | G7: 1 | H7: =F7*G7 -> 57.6 | I7: 20% of the server price (published)
A8: Infrastructure | B8: Shared test system - application container | C8: 12 | D8: 1 | E8: 12 | F8: =C8*D8*E8 -> 144 | G8: 1 | H8: =F8*G8 -> 144 | I8: Published range $5-$12; check Cleveland's bill
A9: Infrastructure | B9: Shared test system - application database | C9: 7 | D9: 1 | E9: 12 | F9: =C9*D9*E9 -> 84 | G9: 1 | H9: =F9*G9 -> 84 | I9: $7 development database; a managed database costs more
A10: Infrastructure | B10: EspoCRM Advanced Pack licence (test CRM) | C10: 395 | D10: 1 | E10: 1 | F10: =C10*D10*E10 -> 395 | G10: =Assumptions!$B$13/C10 -> 0.74683544 | H10: =F10*G10 -> 295 | I10: Standard $395 a year; $295 a year on the EspoCRM nonprofit price (both stated by Doug). One licence may cover a buyer own test and production systems - not settled for the Association
A11: Tools | B11: Google Workspace mailboxes | C11: 7 | D11: =Assumptions!$B$5 -> 2 | E11: 12 | F11: =C11*D11*E11 -> 168 | G11: =Assumptions!$B$11/C11 -> 0 | H11: =F11*G11 -> 0 | I11: $7 per person per month on the annual plan. Free nonprofit edition once qualified (stated by Doug)
A12: Tools | B12: Password vault (Proton Pass Professional) | C12: 4.49 | D12: =Assumptions!$B$6 -> 3 | E12: 12 | F12: =C12*D12*E12 -> 161.64 | G12: 1 | H12: =F12*G12 -> 161.64 | I12: Published third-party summary; Essentials is $1.99
A13: Tools | B13: Request system (ClickUp Unlimited) | C13: 7 | D13: =Assumptions!$B$7 -> 3 | E13: 12 | F13: =C13*D13*E13 -> 252 | G13: 1 | H13: =F13*G13 -> 252 | I13: Published. The free plan may be enough - set quantity to 0 to test that
A14: Tools | B14: AI development tool (Claude Max) | C14: 100 | D14: 1 | E14: 12 | F14: =C14*D14*E14 -> 1200 | G14: =1-Assumptions!$B$10 -> 0.2 | H14: =F14*G14 -> 240 | I14: Published. $200 for the larger plan. Nonprofit discount stated by Doug
A15: Tools | B15: GitHub organization | C15: 0 | D15: 1 | E15: 12 | F15: =C15*D15*E15 -> 0 | G15: 1 | H15: =F15*G15 -> 0 | I15: Free plan
A16: Organization | B16: Directors and officers insurance | C16: 800 | D16: 1 | E16: 1 | F16: =C16*D16*E16 -> 800 | G16: 1 | H16: =F16*G16 -> 800 | I16: Published average. May be $0 if the fiscal sponsor's policy covers sponsored programs
A17: Organization | B17: General liability insurance | C17: 500 | D17: 1 | E17: 1 | F17: =C17*D17*E17 -> 500 | G17: 1 | H17: =F17*G17 -> 500 | I17: Published average. Same note as above
A18: Organization | B18: Cyber liability insurance | C18: 0 | D18: 1 | E18: 1 | F18: =C18*D18*E18 -> 0 | G18: 1 | H18: =F18*G18 -> 0 | I18: PRICE NEEDED - volunteers can reach chapters' systems, which hold client and mentor records
B19: Subtotal — recurring costs | F19: =SUM(F5:F18) -> 4061.24 | H19: =SUM(H5:H18) -> 2833.24

Sheet Annual total
A1: Annual total and dues
A3: Line | B3: Standard prices | C3: With nonprofit programs
A4: Recurring costs (from the previous sheet) | B4: ='Recurring costs'!F19 -> 4061.24 | C4: ='Recurring costs'!H19 -> 2833.24
A5: Fiscal sponsor's fee | B5: =B4/(1-Assumptions!$B$8)-B4 -> 451.24889 | C5: =C4/(1-Assumptions!$B$8)-C4 -> 314.80444
A6: Contingency | B6: =(B4+B5)*Assumptions!$B$9 -> 451.24889 | C6: =(C4+C5)*Assumptions!$B$9 -> 314.80444
A7: Annual total to be covered by dues | B7: =SUM(B4:B6) -> 4963.7378 | C7: =SUM(C4:C6) -> 3462.8489
A9: One-time starting costs
A10: Item | B10: Amount | C10: Note
A11: Ohio articles of incorporation (nonprofit) | B11: 99 | C11: Published
A12: Federal tax-exemption application | B12: =Assumptions!$B$12 -> 600 | C12: $600 full form; $275 short form
A13: Nonprofit attorney review | B13: 0 | C13: PRICE NEEDED - ask for a quote
A14: Total one-time | B14: =SUM(B11:B13) -> 699

Sheet Dues by band
A1: Dues by size band
A2: Ruling 11: larger chapters pay more and carry more votes. Enter the number of chapters in each band and the share each band carries. Dues are the annual total split in proportion to those shares.
A4: Band | B4: Chapters | C4: Share per chapter | D4: Dues per chapter — standard | E4: Dues per chapter — with nonprofit programs | F4: Band total — standard | G4: Band total — with nonprofit programs
A5: Small | B5: 1 | C5: 1 | D5: =IF($B$9=0,0,'Annual total'!$B$7*C5/$B$9) -> 827.28963 | E5: =IF($B$9=0,0,'Annual total'!$C$7*C5/$B$9) -> 577.14148 | F5: =D5*B5 -> 827.28963 | G5: =E5*B5 -> 577.14148
A6: Medium | B6: 1 | C6: 2 | D6: =IF($B$9=0,0,'Annual total'!$B$7*C6/$B$9) -> 1654.5793 | E6: =IF($B$9=0,0,'Annual total'!$C$7*C6/$B$9) -> 1154.283 | F6: =D6*B6 -> 1654.5793 | G6: =E6*B6 -> 1154.283
A7: Large | B7: 1 | C7: 3 | D7: =IF($B$9=0,0,'Annual total'!$B$7*C7/$B$9) -> 2481.8689 | E7: =IF($B$9=0,0,'Annual total'!$C$7*C7/$B$9) -> 1731.4244 | F7: =D7*B7 -> 2481.8689 | G7: =E7*B7 -> 1731.4244
A8: Total chapters | B8: =SUM(B5:B7) -> 3
A9: Total shares | B9: =SUMPRODUCT(B5:B7,C5:C7) -> 6
A10: Total dues collected | F10: =SUM(F5:F7) -> 4963.7378 | G10: =SUM(G5:G7) -> 3462.8489
A12: Example: with one chapter in each band and shares of 1, 2 and 3, the large chapter pays three times what the small one pays.

Sheet Notes and sources
A1: Where each price came from
A3: Topic | B3: Detail
A4: Prices stated by Doug (09-19-26) | B4: EspoCRM Advanced Pack $395 a year. Anthropic offers nonprofits an 80% discount. Google Workspace has a free nonprofit edition once the Association qualifies.
A5: Nonprofit programs | B5: Both nonprofit programs need the Association to qualify as a nonprofit. Under fiscal sponsorship it may not qualify on its own, which is why the workbook keeps both columns.
A6: Google Workspace | B6: $7 per person per month on the annual plan: emailtooltester.com/en/blog/google-workspace-pricing/
A7: DigitalOcean | B7: Server and backup prices: digitalocean.com/pricing/droplets. Application and database prices: digitalocean.com/pricing/app-platform
A8: Proton Pass | B8: ifeeltech.com/blog/proton-pass-business-review
A9: ClickUp | B9: clickup.com/pricing
A10: Claude | B10: claude.com/pricing
A11: Fiscal sponsor fee | B11: 5%-15% of funds received; 3%-8% for the lighter form: holisticunderground.org/fiscal-sponsorship/fees
A12: Insurance | B12: D&O about $800 a year, general liability about $500 a year: insureon.com/nonprofit-business-insurance/cost
A13: Filing fees | B13: Federal: irs.gov Form 1023 user fee. Ohio: $99 articles of incorporation.
A14: Not checked | B14: The test system's application and database prices are estimates. Cleveland's current bill is the better source.

Sheet Chapter costs
A1: What a chapter pays itself, per year
A2: These are the chapter's own costs, paid directly in its own accounts. Association dues are NOT included here: the dues are not decided and are reported separately. Prices assume the chapter qualifies as a nonprofit, since membership is limited to nonprofits. Blue = input, black = calculated.
A4: Item | B4: Unit price | C4: Times per year | D4: Small — quantity | E4: Medium — quantity | F4: Large — quantity | G4: Small — annual | H4: Medium — annual | I4: Large — annual | J4: Note
A5: CRM server (4 GB) | B5: 24 | C5: 12 | D5: 1 | E5: 1 | F5: 1 | G5: =$B5*D5*$C5 -> 288 | H5: =$B5*E5*$C5 -> 288 | I5: =$B5*F5*$C5 -> 288 | J5: Same size as the trial chapter's. A large chapter may need more memory
A6: CRM server backups | B6: 4.8 | C6: 12 | D6: 1 | E6: 1 | F6: 1 | G6: =$B6*D6*$C6 -> 57.6 | H6: =$B6*E6*$C6 -> 57.6 | I6: =$B6*F6*$C6 -> 57.6 | J6: 20 percent of the server price
A7: Application container | B7: 12 | C7: 12 | D7: 1 | E7: 1 | F7: 1 | G7: =$B7*D7*$C7 -> 144 | H7: =$B7*E7*$C7 -> 144 | I7: =$B7*F7*$C7 -> 144 | J7: Published range $5-$12 per month
A8: Application database | B8: 15 | C8: 12 | D8: 1 | E8: 1 | F8: 1 | G8: =$B8*D8*$C8 -> 180 | H8: =$B8*E8*$C8 -> 180 | I8: =$B8*F8*$C8 -> 180 | J8: Managed database for live data; the $7 development database is not suitable for production
A9: Domain name | B9: 11 | C9: 1 | D9: 1 | E9: 1 | F9: 1 | G9: =$B9*D9*$C9 -> 11 | H9: =$B9*E9*$C9 -> 11 | I9: =$B9*F9*$C9 -> 11 | J9: Most chapters already own one, so this may be $0
A10: Domain name records (Cloudflare) | B10: 0 | C10: 1 | D10: 1 | E10: 1 | F10: 1 | G10: =$B10*D10*$C10 -> 0 | H10: =$B10*E10*$C10 -> 0 | I10: =$B10*F10*$C10 -> 0 | J10: Free plan
A11: Google Workspace - staff mailboxes | B11: 0 | C11: 12 | D11: 4 | E11: 10 | F11: 20 | G11: =$B11*D11*$C11 -> 0 | H11: =$B11*E11*$C11 -> 0 | I11: =$B11*F11*$C11 -> 0 | J11: Free nonprofit edition. At standard prices this is $7 per person per month
A12: Google Workspace - mentor mailboxes | B12: 0 | C12: 12 | D12: 10 | E12: 40 | F12: 100 | G12: =$B12*D12*$C12 -> 0 | H12: =$B12*E12*$C12 -> 0 | I12: =$B12*F12*$C12 -> 0 | J12: Free nonprofit edition. Set the quantity to 0 if mentors use their own email
A13: Advanced Pack extension licence | B13: 295 | C13: 1 | D13: 1 | E13: 1 | F13: 1 | G13: =$B13*D13*$C13 -> 295 | H13: =$B13*E13*$C13 -> 295 | I13: =$B13*F13*$C13 -> 295 | J13: Nonprofit price stated by Doug; $395 standard
A14: Google Integration extension licence | B14: 0 | C14: 1 | D14: 1 | E14: 1 | F14: 1 | G14: =$B14*D14*$C14 -> 0 | H14: =$B14*E14*$C14 -> 0 | I14: =$B14*F14*$C14 -> 0 | J14: PRICE NEEDED - required by the network standard
A15: Password vault (Proton Pass) | B15: 4.49 | C15: 12 | D15: 3 | E15: 3 | F15: 5 | G15: =$B15*D15*$C15 -> 161.64 | H15: =$B15*E15*$C15 -> 161.64 | I15: =$B15*F15*$C15 -> 269.4 | J15: Business plans require at least 3 people
A16: Video meeting account (public webinars only) | B16: 16 | C16: 12 | D16: 0 | E16: 1 | F16: 1 | G16: =$B16*D16*$C16 -> 0 | H16: =$B16*E16*$C16 -> 192 | I16: =$B16*F16*$C16 -> 192 | J16: Estimate. Only a chapter that runs public webinars needs one
A17: Chapter's own costs — nonprofit prices | G17: =SUM(G5:G16) -> 1137.24 | H17: =SUM(H5:H16) -> 1329.24 | I17: =SUM(I5:I16) -> 1437
A19: Same chapter at standard prices (no nonprofit status)
A20: Mailboxes at $7 per person per month | G20: =7*12*(D11+D12) -> 1176 | H20: =7*12*(E11+E12) -> 4200 | I20: =7*12*(F11+F12) -> 10080
A21: Advanced Pack at $395 instead of $295 | G21: =395-295 -> 100 | H21: =395-295 -> 100 | I21: =395-295 -> 100
A22: Chapter's own costs — standard prices | G22: =G17+G20+G21 -> 2413.24 | H22: =H17+H20+H21 -> 5629.24 | I22: =I17+I20+I21 -> 11617
A24: Example sizes: small = 4 staff and 10 mentors; medium = 10 staff and 40 mentors; large = 20 staff and 100 mentors. Change any quantity to match a real chapter.
A25: Association dues are on the 'Dues by band' sheet and are not added here.
